promptflow_helpers/__init__.py
promptflow_helpers/chunker.py
promptflow_helpers/cosmos_wrapper.py
promptflow_helpers/helpers.py
promptflow_helpers/nltk_modules.py
promptflow_helpers/openai_wrapper.py
promptflow_helpers-0.2.0.dist-info/METADATA
promptflow_helpers-0.2.0.dist-info/WHEEL
promptflow_helpers-0.2.0.dist-info/RECORD
